examples/advanced_usage.py
examples/basic_usage.py
examples/requirements.txt
waifu2x_python/__init__.py
waifu2x_python/cli.py
waifu2x_python/config.py
waifu2x_python/core.py
waifu2x_python/exceptions.py
waifu2x_python/utils.py
waifu2x_python-2.0.4.dist-info/licenses/AUTHORS.md
waifu2x_python-2.0.4.dist-info/METADATA
waifu2x_python-2.0.4.dist-info/WHEEL
waifu2x_python-2.0.4.dist-info/entry_points.txt
waifu2x_python-2.0.4.dist-info/top_level.txt
waifu2x_python-2.0.4.dist-info/RECORD
