Metadata-Version: 2.4
Name: waifu2x-python
Version: 2.0.4
Summary: High-performance Python wrapper for waifu2x-ncnn-vulkan with GPU/CPU support
Home-page: https://github.com/gleidsonnunes/waifu2x-python
Author: AI Assistant
Author-email: Gleidson Rodrigues Nunes <gleidsonrnunes@gmail.com>
Maintainer: Gleidson Rodrigues Nunes
Maintainer-email: Gleidson Rodrigues Nunes <gleidsonrnunes@gmail.com>
License: MIT
Project-URL: Homepage, https://github.com/gleidsonnunes/waifu2x-python
Project-URL: Documentation, https://github.com/gleidsonnunes/waifu2x-python#readme
Project-URL: Repository, https://github.com/gleidsonnunes/waifu2x-python.git
Project-URL: Bug Tracker, https://github.com/gleidsonnunes/waifu2x-python/issues
Project-URL: Changelog, https://github.com/gleidsonnunes/waifu2x-python/blob/main/CHANGELOG.md
Keywords: waifu2x,super-resolution,image-processing,computer-vision,deep-learning,ncnn,vulkan,upscaling,denoising
Platform: any
Classifier: Development Status :: 4 - Beta
Classifier: Intended Audience :: Developers
Classifier: Intended Audience :: Science/Research
Classifier: License :: OSI Approved :: MIT License
Classifier: Operating System :: OS Independent
Classifier: Programming Language :: Python :: 3
Classifier: Programming Language :: Python :: 3.8
Classifier: Programming Language :: Python :: 3.9
Classifier: Programming Language :: Python :: 3.10
Classifier: Programming Language :: Python :: 3.11
Classifier: Programming Language :: Python :: 3 :: Only
Classifier: Topic :: Scientific/Engineering
Classifier: Topic :: Scientific/Engineering :: Image Processing
Classifier: Topic :: Scientific/Engineering :: Image Recognition
Classifier: Topic :: Multimedia :: Graphics
Classifier: Topic :: Multimedia :: Graphics :: Graphics Conversion
Classifier: Typing :: Typed
Requires-Python: >=3.8
License-File: AUTHORS.md
Requires-Dist: opencv-python>=4.8.0
Requires-Dist: numpy>=1.24.0
Requires-Dist: Pillow>=10.0.0
Provides-Extra: dev
Requires-Dist: pytest>=7.4.0; extra == "dev"
Requires-Dist: pytest-cov>=4.1.0; extra == "dev"
Requires-Dist: black>=23.3.0; extra == "dev"
Requires-Dist: flake8>=6.0.0; extra == "dev"
Requires-Dist: mypy>=1.4.1; extra == "dev"
Requires-Dist: isort>=5.12.0; extra == "dev"
Requires-Dist: pytest-mock>=3.10.0; extra == "dev"
Requires-Dist: pytest-asyncio>=0.21.0; extra == "dev"
Provides-Extra: docs
Requires-Dist: sphinx>=6.0.0; extra == "docs"
Requires-Dist: sphinx-rtd-theme>=1.2.0; extra == "docs"
Requires-Dist: sphinx-autodoc-typehints>=1.22.0; extra == "docs"
Requires-Dist: myst-parser>=1.0.0; extra == "docs"
Dynamic: home-page
Dynamic: license-file
Dynamic: maintainer
Dynamic: platform
Dynamic: requires-python
